{
    "basic_info": {
      "name": "Timothy Jan",
      "titles": [ "Software Engineer", "Full-Stack Developer", "Front-end Developer", "Back-end Developer"],
      "social": [
        {
          "name": "github",
          "url": "https://github.com/TimothyJan",
          "class": "fab fa-github"
        },
        {
          "name": "linkedin",
          "url": "https://www.linkedin.com/in/timothy-jan-533212108/",
          "class": "fab fa-linkedin-in"
        }
      ],
      "image": "myProfile.jpg"
    },
    "skills": {
      "icons": [
        {
          "name": "Python",
          "class": "devicon-python-plain",
          "level": "80"
        },
        {
          "name": "C++",
          "class": "devicon-cplusplus-plain",
          "level": "80"
        },
        {
          "name": "JavaScript",
          "class": "devicon-javascript-plain",
          "level": "60"
        },
        {
          "name": "NodeJS",
          "class": "devicon-nodejs-plain",
          "level": "80"
        },
        {
          "name": "ExpressJS",
          "class": "devicon-express-original",
          "level": "80"
        },
        {
          "name": "React",
          "class": "devicon-react-original",
          "level": "60"
        },
        {
          "name": "Angular",
          "class": "devicon-angularjs-plain",
          "level": "60"
        },
        {
          "name": "TypeScript",
          "class": "devicon-typescript-plain",
          "level": "60"
        },
        {
          "name": "Django",
          "class": "devicon-django-plain",
          "level": "75"
        },
        {
          "name": "Git",
          "class": "devicon-git-plain",
          "level": "90"
        },
        {
          "name": "Github",
          "class": "devicon-github-original",
          "level": "90"
        },
        {
          "name": "Bootstrap",
          "class": "devicon-bootstrap-plain",
          "level": "85"
        },
        {
          "name": "Tensorflow",
          "class": "devicon-tensorflow-original",
          "level": "80"
        },
        {
          "name": "MongoDb",
          "class": "devicon-mongodb-plain",
          "level": "60"
        },
        {
          "name": "HTML 5",
          "class": "devicon-html5-plain",
          "level": "95"
        },
        {
          "name": "CSS 3",
          "class": "devicon-css3-plain",
          "level": "95"
        }
      ]
    }
  }